{"development_contributing.md":"435166ac","es_index.md":"926dea44","about_community.md":"899a2775","about_privacy-statement.md":"a5be7d6e","es_development_local.md":"43e06abc","about_pricing.md":"468c7e54","es_development_contributing.md":"3c94b29c","integrations_webhooks.md":"22aaee7b","integrations_obsidian.md":"b96be2f9","es_integrations_api.md":"d7b2d228","zh_using_reading.md":"812c3191","zh_using_rules.md":"e190dc8e","zh_using_saved-searches.md":"d03401ea","zh_using_saving.md":"fa2d5223","zh_using_search.md":"22a5977c","zh_using_text-to-speech.md":"6a1d0e3b","ko_using_search.md":"038e52c7","integrations_api.md":"d471ae9c","integrations_logseq.md":"fbd0717f","index.md":"1f13bcbd","es_integrations_obsidian.md":"a3e0b6d0","development_local.md":"1b1226b9","es_integrations_webhooks.md":"580c1ce0","es_self-hosting_self-hosting.md":"0a2464bf","es_using_help.md":"fa90ba56","es_using_importing.md":"6b9dbf2c","ko_using_text-to-speech.md":"c0a10ef6","self-hosting_self-hosting.md":"6f0ca9c1","ko_integrations_logseq.md":"e49713ed","using_exporting.md":"494e01a8","using_feeds.md":"ebdcf55d","using_help.md":"bd3218c1","zh_development_local.md":"2e191879","using_importing.md":"277ed174","using_rules.md":"61e89eca","using_organizing.md":"987202e9","using_text-to-speech.md":"94b047e8","using_saved-searches.md":"c9f8107a","using_search.md":"254bd897","using_welcome-to-omnivore.md":"7e38227c","ko_using_help.md":"16150b20","ko_using_importing.md":"dbd35a71","ko_using_inbox.md":"650c67e1","ko_using_install.md":"fe7b0f79","ko_using_keyboard.md":"192f4e7e","using_keyboard.md":"bad63ca6","zh_integrations_webhooks.md":"1a99a09c","using_inbox.md":"53d2d6f5","ko_integrations_obsidian.md":"1d198270","using_managing-account.md":"430e8c7f","ko_using_saving.md":"3a736696","zh_integrations_obsidian.md":"36b78d16","ko_integrations_webhooks.md":"bd820e85","about_privacy-policy.md":"2d532efe","zh_integrations_api.md":"92c74ba9","using_saving.md":"c776dcc7","zh_self-hosting_self-hosting.md":"89cacd0a","zh_using_help.md":"dd932bca","zh_using_importing.md":"07d611be","zh_using_inbox.md":"748d7ad4","zh_using_install.md":"cefc1888","zh_using_managing-account.md":"fabae015","zh_using_organizing.md":"a02fd886","zh_using_keyboard.md":"c36080c2","ko_using_managing-account.md":"1fdac71f","ko_using_organizing.md":"01b5f8bd","ko_using_reading.md":"decf20d7","ko_using_rules.md":"6cf96c66","ko_index.md":"7007f9c9","ko_using_saved-searches.md":"0e12b479","about_press.md":"dccc72cd","es_using_inbox.md":"62d9cc00","using_install.md":"6374d2ba","es_using_install.md":"d47415ca","es_using_reading.md":"bb1bb474","es_using_managing-account.md":"408971c9","zh_index.md":"2d7b5329","ko_integrations_api.md":"fa1b733a","es_using_keyboard.md":"b2e57c18","es_integrations_logseq.md":"46a44408","es_using_rules.md":"5c9b928a","es_using_saved-searches.md":"6d0f24ff","zh_development_contributing.md":"bbc439e4","es_using_saving.md":"2fc0f25c","es_using_search.md":"5b668616","es_using_text-to-speech.md":"093cef1a","es_using_organizing.md":"861c54ce","using_reading.md":"52f23daa","zh_integrations_logseq.md":"add659e5"}
